serenata_toolbox/__init__.py
serenata_toolbox/settings.py
serenata_toolbox/chamber_of_deputies/__init__.py
serenata_toolbox/chamber_of_deputies/deputies_dataset.py
serenata_toolbox/chamber_of_deputies/official_missions_dataset.py
serenata_toolbox/chamber_of_deputies/presences_dataset.py
serenata_toolbox/chamber_of_deputies/reimbursements.py
serenata_toolbox/chamber_of_deputies/reimbursements_cleaner.py
serenata_toolbox/chamber_of_deputies/session_start_times_dataset.py
serenata_toolbox/chamber_of_deputies/speeches_dataset.py
serenata_toolbox/datasets/__init__.py
serenata_toolbox/datasets/contextmanager.py
serenata_toolbox/datasets/downloader.py
serenata_toolbox/datasets/helpers.py
serenata_toolbox/datasets/local.py
serenata_toolbox/federal_senate/__init__.py
serenata_toolbox/federal_senate/dataset.py
serenata_toolbox-15.1.6.data/scripts/serenata-toolbox
serenata_toolbox-15.1.6.dist-info/LICENSE
serenata_toolbox-15.1.6.dist-info/METADATA
serenata_toolbox-15.1.6.dist-info/WHEEL
serenata_toolbox-15.1.6.dist-info/top_level.txt
serenata_toolbox-15.1.6.dist-info/RECORD
