Metadata-Version: 2.1
Name: serenata-toolbox
Version: 15.1.6
Summary: Toolbox for Serenata de Amor project
Home-page: http://github.com/okfn-brasil/serenata-toolbox
Author: Serenata de Amor
Author-email: contato@serenata.ai
License: MIT
Keywords: serenata de amor,data science,brazil,corruption
Platform: UNKNOWN
Classifier: Development Status :: 4 - Beta
Classifier: Intended Audience :: Science/Research
Classifier: License :: OSI Approved :: MIT License
Classifier: Programming Language :: Python :: 3.6
Classifier: Programming Language :: Python :: 3.7
Classifier: Programming Language :: Python :: 3.8
Classifier: Topic :: Utilities
Requires-Python: >=3.6
Requires-Dist: aiofiles
Requires-Dist: aiohttp
Requires-Dist: beautifulsoup4 (>=4.4)
Requires-Dist: lxml (>=3.6)
Requires-Dist: pandas (>=0.18)
Requires-Dist: python-decouple (>=3.1)
Requires-Dist: tqdm
